{
  "ad3b83f2-c20f-4870-9321-bf0298942700": {
    "applicationId": "cda9cb8e-02ff-4dcf-91a3-2d92179783af",
    "applicationKey": "arq-lab-g-v2-hist-015",
    "applicationName": "branch-private-key-divergence",
    "authorEmail": "lab@arq.local",
    "authorName": "ARQ Lab",
    "authoredAt": "2026-04-01T18:10:16Z",
    "branchName": "feature/private-key-hotfix",
    "commitSha": "8c98762e326a552f0f07154f0b337e1ab412d9ab",
    "committedAt": "2026-04-01T18:10:16Z",
    "committerEmail": "lab@arq.local",
    "committerName": "ARQ Lab",
    "contextClassification": "COMMENT",
    "detectionSource": "REGEX",
    "detectionState": "ACTIVE",
    "evidenceExcerpt": "-----BEGIN RSA PRIVATE KEY-----\nMIIEow************************K5pQ==\n-----END RSA PRIVATE KEY-----",
    "evidenceJson": null,
    "explainability": {
      "detectionSource": "REGEX",
      "queryFamily": null,
      "rawEvidenceJson": null,
      "resolutionScope": null,
      "resolvedValue": null,
      "semanticKey": null
    },
    "exposureScope": "HEAD_ONLY",
    "findingId": "ad3b83f2-c20f-4870-9321-bf0298942700",
    "findingKind": "SECRET",
    "firstSeenAt": "2026-04-01T18:10:58.751524Z",
    "firstSeenCommitSha": "8c98762e326a552f0f07154f0b337e1ab412d9ab",
    "firstSeenRefName": "feature/private-key-hotfix",
    "firstSeenScanRunId": "3a351919-9c1e-494a-85bd-fe7d3cffaab7",
    "history": [
      {
        "actorId": "3287fe24-9374-407e-a1a1-5f64ec51794b",
        "actorType": "SERVICE",
        "detectionStateFrom": null,
        "detectionStateTo": "ACTIVE",
        "effectiveStatusFrom": null,
        "effectiveStatusTo": "IN_PROGRESS",
        "eventId": "25495295-7a02-4427-a0ed-dddeb5810d17",
        "eventType": "DETECTED",
        "occurredAt": "2026-04-01T18:10:58.756081Z",
        "scanRunId": "3a351919-9c1e-494a-85bd-fe7d3cffaab7",
        "summary": "Finding detected during scan.",
        "workflowStatusFrom": null,
        "workflowStatusTo": "IN_PROGRESS"
      }
    ],
    "lastSeenAt": "2026-04-01T18:10:58.751524Z",
    "lastSeenCommitSha": "8c98762e326a552f0f07154f0b337e1ab412d9ab",
    "lastSeenRefName": "feature/private-key-hotfix",
    "lastSeenScanRunId": "3a351919-9c1e-494a-85bd-fe7d3cffaab7",
    "module": "guardian",
    "occurrenceCount": 1,
    "occurrences": [
      {
        "authorEmail": "lab@arq.local",
        "authorName": "ARQ Lab",
        "authoredAt": "2026-04-01T18:10:16Z",
        "canonical": true,
        "commitSha": "8c98762e326a552f0f07154f0b337e1ab412d9ab",
        "committedAt": "2026-04-01T18:10:16Z",
        "committerEmail": "lab@arq.local",
        "committerName": "ARQ Lab",
        "contextClassification": "COMMENT",
        "detectionSource": "REGEX",
        "evidenceExcerpt": "-----BEGIN RSA PRIVATE KEY-----\nMIIEow************************K5pQ==\n-----END RSA PRIVATE KEY-----",
        "evidenceJson": null,
        "explainability": {
          "detectionSource": "REGEX",
          "queryFamily": null,
          "rawEvidenceJson": null,
          "resolutionScope": null,
          "resolvedValue": null,
          "semanticKey": null
        },
        "filePath": "ops/keys/feature-private.pem",
        "lineEnd": 10,
        "lineStart": 1,
        "observedAt": "2026-04-01T18:10:58.755558Z",
        "occurrenceId": "266ef27a-e186-4a1c-8c0a-81c20f664f5f",
        "occurrenceScope": "HEAD",
        "refName": "feature/private-key-hotfix",
        "scanRunId": "3a351919-9c1e-494a-85bd-fe7d3cffaab7",
        "semanticKey": null
      }
    ],
    "presentInHistory": false,
    "presentOnHead": true,
    "primaryFilePath": "ops/keys/feature-private.pem",
    "primaryLineEnd": 10,
    "primaryLineStart": 1,
    "projectId": "e47d6679-e8dc-4ad1-878c-10a86b629b13",
    "projectKey": "arq-lab",
    "projectName": "ARQ Lab Validation",
    "repositorySourceId": "a14e7593-baea-4b3e-98d2-7623abe68baa",
    "resolvedAt": null,
    "ruleKey": "guardian.private-key",
    "ruleName": "Private Key",
    "semanticKey": null,
    "severity": "CRITICAL",
    "status": "IN_PROGRESS",
    "workflowStatus": "IN_PROGRESS"
  }
}