{
  "plan": {
    "branchScope": "SINGLE_BRANCH",
    "modules": [
      "guardian"
    ],
    "name": "guardian-head-main",
    "refName": "main",
    "scanMode": "HEAD_SNAPSHOT"
  },
  "queued": {
    "applicationId": "6bb20ec5-087e-4e04-90ff-323a544d240b",
    "applicationKey": "arq-lab-g-v2-hist-001",
    "applicationName": "payments-history-lineage",
    "branchScope": "SINGLE_BRANCH",
    "commitSha": null,
    "connectorId": null,
    "connectorName": null,
    "createdAt": "2026-04-03T07:04:04.204962900Z",
    "currentFile": null,
    "currentPhase": "QUEUED",
    "currentRepository": "https://github.com/ARQ-Sec/payments-history-lineage.git",
    "failureCode": null,
    "failureMessage": null,
    "filesScanned": 0,
    "filesTotal": 0,
    "finishedAt": null,
    "id": "b6486ee2-65f3-4004-914e-98709a977b96",
    "modules": [
      {
        "findingCount": 0,
        "module": "guardian",
        "occurrenceCount": 0,
        "suppressedCount": 0
      }
    ],
    "parentScanRunId": null,
    "progressPercent": 0,
    "requestedRefName": "main",
    "scanMode": "HEAD_SNAPSHOT",
    "scanType": "APPLICATION",
    "scannedRefName": null,
    "startedAt": null,
    "status": "QUEUED",
    "summary": {},
    "workerNode": null
  }
}