{
  "auditArtifacts": {
    "dossierMissing": false,
    "dossierPath": "C:\\Users\\EnesPekdas\\Desktop\\ARQV2\\LAB\\Arq-lab\\generated\\Q-V4-PY-001\\validation\\generated-project-dossier.md",
    "fillerRatio": 0.9355221518987342,
    "generatedManifestPath": "C:\\Users\\EnesPekdas\\Desktop\\ARQV2\\LAB\\Arq-lab\\generated\\Q-V4-PY-001\\validation\\generated-file-manifest.json",
    "generatedTreePath": "C:\\Users\\EnesPekdas\\Desktop\\ARQV2\\LAB\\Arq-lab\\generated\\Q-V4-PY-001\\validation\\generated-tree.txt",
    "locComposition": {
      "docs": 11,
      "fixtures": 0,
      "live business code": 98,
      "live config": 0,
      "scripts": 1,
      "synthetic filler / inflation content": 4730,
      "tests": 32,
      "total": 5056,
      "vendor/generated": 169
    },
    "projectLocalDossierPath": "C:\\Users\\EnesPekdas\\Desktop\\ARQV2\\LAB\\Arq-lab\\repositories\\notification-signer-python\\validation\\generated-project-dossier.md",
    "realismJustification": "build/test/smoke contracts execute successfully; synthetic filler is materially visible and pulls realism down",
    "realismScore": 1,
    "reportDossierPath": "C:\\Users\\EnesPekdas\\Desktop\\ARQV2\\LAB\\Arq-lab\\reports\\generated-project-dossiers\\Q-V4-PY-001.md",
    "runnabilityLogRootPath": "C:\\Users\\EnesPekdas\\Desktop\\ARQV2\\LAB\\Arq-lab\\repositories\\notification-signer-python\\validation\\runnability-logs"
  },
  "cleanExpectedMatches": 2,
  "explainabilityFailures": [],
  "extraFindings": [],
  "finalVerdict": "PASS_WITH_NOISE",
  "finalVerdictReason": "20 unexpected/noisy finding(s) remained after matching (same-surface-extra=20, regex-only=9)",
  "followUpAction": "review findings",
  "matchedFindings": [
    {
      "actual": {
        "branchName": "main",
        "detectionSource": "AST",
        "evidenceExcerpt": "return hashlib.md5(payload).hexdigest()",
        "exposureScope": "HEAD_ONLY",
        "findingId": "2b06bade-baa6-4a8e-a50f-e0c33fed1191",
        "findingKind": "VULNERABILITY",
        "module": "quantum",
        "presentInHistory": false,
        "presentOnHead": true,
        "primaryFilePath": "app/security/legacy_signature.py",
        "queryFamily": "python.hashlib",
        "rawEvidenceJson": "{\"queryRef\":\"python.hashlib.weak-digest\",\"callName\":\"hashlib.md5\",\"resolutionScope\":\"SAME_FUNCTION\",\"resolvedValue\":\"MD5\",\"importStyle\":\"MODULE\"}",
        "resolutionScope": "SAME_FUNCTION",
        "resolvedValue": "MD5",
        "ruleKey": "quantum.arq-q-0262-python",
        "ruleName": "hashlib: MD5/SHA1-based password hashing (no salt/stretch)",
        "scanMode": "HEAD_SNAPSHOT",
        "scanPlanName": "quantum-head",
        "semanticKey": "python:hashlib:hashlib.md5:MD5",
        "severity": "CRITICAL"
      },
      "expected": "md5"
    },
    {
      "actual": {
        "branchName": "main",
        "detectionSource": "HYBRID",
        "evidenceExcerpt": "generator = random.Random()",
        "exposureScope": "HEAD_ONLY",
        "findingId": "3cc7e90f-2079-4def-ae2c-ffe8e945acb9",
        "findingKind": "VULNERABILITY",
        "module": "quantum",
        "presentInHistory": false,
        "presentOnHead": true,
        "primaryFilePath": "app/security/token_factory.py",
        "queryFamily": "python.call-name-match",
        "rawEvidenceJson": "{\"queryRef\":\"python.call-name-match\",\"callName\":\"random.Random\",\"resolutionScope\":\"SAME_FUNCTION\",\"resolvedValue\":\"random.Random\",\"fullName\":\"random.Random\"}",
        "resolutionScope": "SAME_FUNCTION",
        "resolvedValue": "random.Random",
        "ruleKey": "quantum.arq-q-0260-python",
        "ruleName": "random: non-cryptographic RNG for security purposes",
        "scanMode": "HEAD_SNAPSHOT",
        "scanPlanName": "quantum-head",
        "semanticKey": "python:rng:random.Random:random.Random",
        "severity": "HIGH"
      },
      "expected": "weak-token"
    }
  ],
  "mayFindReview": [],
  "milestone": "M4",
  "missingExpectedFindings": [],
  "module": "quantum",
  "mustFindExpected": 2,
  "mustFindMatched": 2,
  "mustFindMissing": [],
  "mustNotFindViolations": [],
  "noiseBreakdown": {
    "reviewOnlyFindings": 0,
    "sameFileDifferentSignalFindings": 0,
    "sameSurfaceExtraFindings": 20,
    "totallyUnexpectedFindings": 0,
    "unexpectedRegexOnlyFindings": 9
  },
  "noiseCount": 20,
  "normalizationStats": {
    "collapsedDuplicates": 0,
    "normalizedFindings": 22,
    "rawFindings": 22
  },
  "refStateFailures": [],
  "runnability": {
    "build": "passed",
    "smoke": "passed",
    "test": "passed"
  },
  "safeControlViolations": [],
  "sameFileDifferentSignalFindings": [],
  "sameSurfaceExtraFindings": [
    {
      "branchName": "main",
      "detectionSource": "HYBRID",
      "evidenceExcerpt": "return hashlib.md5(payload).hexdigest()",
      "exposureScope": "HEAD_ONLY",
      "findingId": "6ca049fe-d1b8-4e4d-90c0-366295bdb161",
      "findingKind": "VULNERABILITY",
      "module": "quantum",
      "presentInHistory": false,
      "presentOnHead": true,
      "primaryFilePath": "app/security/legacy_signature.py",
      "queryFamily": "python.hashlib",
      "rawEvidenceJson": "{\"queryRef\":\"python.hashlib.weak-digest\",\"callName\":\"hashlib.md5\",\"resolutionScope\":\"SAME_FUNCTION\",\"resolvedValue\":\"MD5\",\"importStyle\":\"MODULE\"}",
      "resolutionScope": "SAME_FUNCTION",
      "resolvedValue": "MD5",
      "ruleKey": "quantum.arq-q-0248-python",
      "ruleName": "hashlib: MD5 digest usage",
      "scanMode": "HEAD_SNAPSHOT",
      "scanPlanName": "quantum-head",
      "semanticKey": "python:hashlib:hashlib.md5:MD5",
      "severity": "HIGH"
    },
    {
      "branchName": "main",
      "detectionSource": "REGEX",
      "evidenceExcerpt": "return hashlib.md5(payload).hexdigest()",
      "exposureScope": "HEAD_ONLY",
      "findingId": "d7975d8a-d305-4841-a92b-bac2b926087b",
      "findingKind": "VULNERABILITY",
      "module": "quantum",
      "presentInHistory": false,
      "presentOnHead": true,
      "primaryFilePath": "app/security/legacy_signature.py",
      "queryFamily": null,
      "rawEvidenceJson": null,
      "resolutionScope": null,
      "resolvedValue": null,
      "ruleKey": "quantum.arq-q-0258-python",
      "ruleName": "hmac: HMAC-MD5 usage",
      "scanMode": "HEAD_SNAPSHOT",
      "scanPlanName": "quantum-head",
      "semanticKey": null,
      "severity": "HIGH"
    },
    {
      "branchName": "main",
      "detectionSource": "HYBRID",
      "evidenceExcerpt": "return hashlib.md5(payload).hexdigest()",
      "exposureScope": "HEAD_ONLY",
      "findingId": "e91af9ce-a19e-4a5d-a74c-468f4d300cb0",
      "findingKind": "VULNERABILITY",
      "module": "quantum",
      "presentInHistory": false,
      "presentOnHead": true,
      "primaryFilePath": "app/security/legacy_signature.py",
      "queryFamily": "python.hashlib",
      "rawEvidenceJson": "{\"queryRef\":\"python.hashlib.weak-digest\",\"callName\":\"hashlib.md5\",\"resolutionScope\":\"SAME_FUNCTION\",\"resolvedValue\":\"MD5\",\"importStyle\":\"MODULE\"}",
      "resolutionScope": "SAME_FUNCTION",
      "resolvedValue": "MD5",
      "ruleKey": "quantum.arq-q-0271-python",
      "ruleName": "hashlib: MD5 usage",
      "scanMode": "HEAD_SNAPSHOT",
      "scanPlanName": "quantum-head",
      "semanticKey": "python:hashlib:hashlib.md5:MD5",
      "severity": "HIGH"
    },
    {
      "branchName": "main",
      "detectionSource": "REGEX",
      "evidenceExcerpt": "return hashlib.md5(payload).hexdigest()",
      "exposureScope": "HEAD_ONLY",
      "findingId": "403209a6-c4b2-445c-97d1-740995dd01c1",
      "findingKind": "VULNERABILITY",
      "module": "quantum",
      "presentInHistory": false,
      "presentOnHead": true,
      "primaryFilePath": "app/security/legacy_signature.py",
      "queryFamily": null,
      "rawEvidenceJson": null,
      "resolutionScope": null,
      "resolvedValue": null,
      "ruleKey": "quantum.arq-q-0277-python",
      "ruleName": "hmac: HMAC with MD5",
      "scanMode": "HEAD_SNAPSHOT",
      "scanPlanName": "quantum-head",
      "semanticKey": null,
      "severity": "HIGH"
    },
    {
      "branchName": "main",
      "detectionSource": "HYBRID",
      "evidenceExcerpt": "return hashlib.md5(payload).hexdigest()",
      "exposureScope": "HEAD_ONLY",
      "findingId": "c4a95240-fcf4-45a6-900d-b6e09d59d235",
      "findingKind": "VULNERABILITY",
      "module": "quantum",
      "presentInHistory": false,
      "presentOnHead": true,
      "primaryFilePath": "app/security/legacy_signature.py",
      "queryFamily": "python.hashlib",
      "rawEvidenceJson": "{\"queryRef\":\"python.hashlib.weak-digest\",\"callName\":\"hashlib.md5\",\"resolutionScope\":\"SAME_FUNCTION\",\"resolvedValue\":\"MD5\",\"importStyle\":\"MODULE\"}",
      "resolutionScope": "SAME_FUNCTION",
      "resolvedValue": "MD5",
      "ruleKey": "quantum.arq-q-0285-python",
      "ruleName": "hashlib: MD5 usage",
      "scanMode": "HEAD_SNAPSHOT",
      "scanPlanName": "quantum-head",
      "semanticKey": "python:hashlib:hashlib.md5:MD5",
      "severity": "HIGH"
    },
    {
      "branchName": "main",
      "detectionSource": "HYBRID",
      "evidenceExcerpt": "return hashlib.md5(payload).hexdigest()",
      "exposureScope": "HEAD_ONLY",
      "findingId": "9e5cca28-2d45-4d52-b65b-7824cc97da42",
      "findingKind": "VULNERABILITY",
      "module": "quantum",
      "presentInHistory": false,
      "presentOnHead": true,
      "primaryFilePath": "app/security/legacy_signature.py",
      "queryFamily": "python.hashlib",
      "rawEvidenceJson": "{\"queryRef\":\"python.hashlib.weak-digest\",\"callName\":\"hashlib.md5\",\"resolutionScope\":\"SAME_FUNCTION\",\"resolvedValue\":\"MD5\",\"importStyle\":\"MODULE\"}",
      "resolutionScope": "SAME_FUNCTION",
      "resolvedValue": "MD5",
      "ruleKey": "quantum.arq-q-0306-python",
      "ruleName": "hashlib: MD5 / SHA1 usage",
      "scanMode": "HEAD_SNAPSHOT",
      "scanPlanName": "quantum-head",
      "semanticKey": "python:hashlib:hashlib.md5:MD5",
      "severity": "HIGH"
    },
    {
      "branchName": "main",
      "detectionSource": "REGEX",
      "evidenceExcerpt": "return hashlib.md5(payload).hexdigest()",
      "exposureScope": "HEAD_ONLY",
      "findingId": "3dabe171-28f8-4010-82cd-3ba8ae41f713",
      "findingKind": "VULNERABILITY",
      "module": "quantum",
      "presentInHistory": false,
      "presentOnHead": true,
      "primaryFilePath": "app/security/legacy_signature.py",
      "queryFamily": null,
      "rawEvidenceJson": null,
      "resolutionScope": null,
      "resolvedValue": null,
      "ruleKey": "quantum.arq-q-0307-python",
      "ruleName": "hashlib: usedforsecurity=False hint misuse",
      "scanMode": "HEAD_SNAPSHOT",
      "scanPlanName": "quantum-head",
      "semanticKey": null,
      "severity": "HIGH"
    },
    {
      "branchName": "main",
      "detectionSource": "HYBRID",
      "evidenceExcerpt": "return hashlib.md5(payload).hexdigest()",
      "exposureScope": "HEAD_ONLY",
      "findingId": "5ae2f357-ccc7-47cc-8ebc-94e79866ed50",
      "findingKind": "VULNERABILITY",
      "module": "quantum",
      "presentInHistory": false,
      "presentOnHead": true,
      "primaryFilePath": "app/security/legacy_signature.py",
      "queryFamily": "python.hashlib",
      "rawEvidenceJson": "{\"queryRef\":\"python.hashlib.weak-digest\",\"callName\":\"hashlib.md5\",\"resolutionScope\":\"SAME_FUNCTION\",\"resolvedValue\":\"MD5\",\"importStyle\":\"MODULE\"}",
      "resolutionScope": "SAME_FUNCTION",
      "resolvedValue": "MD5",
      "ruleKey": "quantum.arq-q-0330-python",
      "ruleName": "hashlib: MD5 / SHA1 usage (critical in mature Python)",
      "scanMode": "HEAD_SNAPSHOT",
      "scanPlanName": "quantum-head",
      "semanticKey": "python:hashlib:hashlib.md5:MD5",
      "severity": "HIGH"
    },
    {
      "branchName": "main",
      "detectionSource": "HYBRID",
      "evidenceExcerpt": "return hashlib.md5(payload).hexdigest()",
      "exposureScope": "HEAD_ONLY",
      "findingId": "c1ab22e9-bc1e-44e2-a0af-58c433116a7b",
      "findingKind": "VULNERABILITY",
      "module": "quantum",
      "presentInHistory": false,
      "presentOnHead": true,
      "primaryFilePath": "app/security/legacy_signature.py",
      "queryFamily": "python.hashlib",
      "rawEvidenceJson": "{\"queryRef\":\"python.hashlib.weak-digest\",\"callName\":\"hashlib.md5\",\"resolutionScope\":\"SAME_FUNCTION\",\"resolvedValue\":\"MD5\",\"importStyle\":\"MODULE\"}",
      "resolutionScope": "SAME_FUNCTION",
      "resolvedValue": "MD5",
      "ruleKey": "quantum.arq-q-0353-python",
      "ruleName": "hashlib: MD5 / SHA1 (critical in PQC-era Python)",
      "scanMode": "HEAD_SNAPSHOT",
      "scanPlanName": "quantum-head",
      "semanticKey": "python:hashlib:hashlib.md5:MD5",
      "severity": "HIGH"
    },
    {
      "branchName": "main",
      "detectionSource": "REGEX",
      "evidenceExcerpt": "import random",
      "exposureScope": "HEAD_ONLY",
      "findingId": "2535c947-99b6-4ff7-8e3a-a8a1bfa60f61",
      "findingKind": "VULNERABILITY",
      "module": "quantum",
      "presentInHistory": false,
      "presentOnHead": true,
      "primaryFilePath": "app/security/token_factory.py",
      "queryFamily": null,
      "rawEvidenceJson": null,
      "resolutionScope": null,
      "resolvedValue": null,
      "ruleKey": "quantum.arq-q-0260-python",
      "ruleName": "random: non-cryptographic RNG for security purposes",
      "scanMode": "HEAD_SNAPSHOT",
      "scanPlanName": "quantum-head",
      "semanticKey": null,
      "severity": "HIGH"
    },
    {
      "branchName": "main",
      "detectionSource": "HYBRID",
      "evidenceExcerpt": "generator = random.Random()",
      "exposureScope": "HEAD_ONLY",
      "findingId": "baa0b024-88c2-423d-a170-2509ce351427",
      "findingKind": "VULNERABILITY",
      "module": "quantum",
      "presentInHistory": false,
      "presentOnHead": true,
      "primaryFilePath": "app/security/token_factory.py",
      "queryFamily": "python.call-name-match",
      "rawEvidenceJson": "{\"queryRef\":\"python.call-name-match\",\"callName\":\"random.Random\",\"resolutionScope\":\"SAME_FUNCTION\",\"resolvedValue\":\"random.Random\",\"fullName\":\"random.Random\"}",
      "resolutionScope": "SAME_FUNCTION",
      "resolvedValue": "random.Random",
      "ruleKey": "quantum.arq-q-0278-python",
      "ruleName": "random: non-cryptographic RNG",
      "scanMode": "HEAD_SNAPSHOT",
      "scanPlanName": "quantum-head",
      "semanticKey": "python:rng:random.Random:random.Random",
      "severity": "HIGH"
    },
    {
      "branchName": "main",
      "detectionSource": "REGEX",
      "evidenceExcerpt": "import random",
      "exposureScope": "HEAD_ONLY",
      "findingId": "c8bd421c-99ce-4237-8a9f-85784b3dfaf9",
      "findingKind": "VULNERABILITY",
      "module": "quantum",
      "presentInHistory": false,
      "presentOnHead": true,
      "primaryFilePath": "app/security/token_factory.py",
      "queryFamily": null,
      "rawEvidenceJson": null,
      "resolutionScope": null,
      "resolvedValue": null,
      "ruleKey": "quantum.arq-q-0278-python",
      "ruleName": "random: non-cryptographic RNG",
      "scanMode": "HEAD_SNAPSHOT",
      "scanPlanName": "quantum-head",
      "semanticKey": null,
      "severity": "HIGH"
    },
    {
      "branchName": "main",
      "detectionSource": "HYBRID",
      "evidenceExcerpt": "generator = random.Random()",
      "exposureScope": "HEAD_ONLY",
      "findingId": "3a41a1d2-c849-4126-b552-1759b73928b5",
      "findingKind": "VULNERABILITY",
      "module": "quantum",
      "presentInHistory": false,
      "presentOnHead": true,
      "primaryFilePath": "app/security/token_factory.py",
      "queryFamily": "python.call-name-match",
      "rawEvidenceJson": "{\"queryRef\":\"python.call-name-match\",\"callName\":\"random.Random\",\"resolutionScope\":\"SAME_FUNCTION\",\"resolvedValue\":\"random.Random\",\"fullName\":\"random.Random\"}",
      "resolutionScope": "SAME_FUNCTION",
      "resolvedValue": "random.Random",
      "ruleKey": "quantum.arq-q-0297-python",
      "ruleName": "random: non-cryptographic RNG",
      "scanMode": "HEAD_SNAPSHOT",
      "scanPlanName": "quantum-head",
      "semanticKey": "python:rng:random.Random:random.Random",
      "severity": "HIGH"
    },
    {
      "branchName": "main",
      "detectionSource": "REGEX",
      "evidenceExcerpt": "import random",
      "exposureScope": "HEAD_ONLY",
      "findingId": "692d45bb-d895-44da-8ff9-abf94649e5d8",
      "findingKind": "VULNERABILITY",
      "module": "quantum",
      "presentInHistory": false,
      "presentOnHead": true,
      "primaryFilePath": "app/security/token_factory.py",
      "queryFamily": null,
      "rawEvidenceJson": null,
      "resolutionScope": null,
      "resolvedValue": null,
      "ruleKey": "quantum.arq-q-0297-python",
      "ruleName": "random: non-cryptographic RNG",
      "scanMode": "HEAD_SNAPSHOT",
      "scanPlanName": "quantum-head",
      "semanticKey": null,
      "severity": "HIGH"
    },
    {
      "branchName": "main",
      "detectionSource": "REGEX",
      "evidenceExcerpt": "import random",
      "exposureScope": "HEAD_ONLY",
      "findingId": "a0c424be-ed3d-4963-9d74-bcc9fd7fd5ad",
      "findingKind": "VULNERABILITY",
      "module": "quantum",
      "presentInHistory": false,
      "presentOnHead": true,
      "primaryFilePath": "app/security/token_factory.py",
      "queryFamily": null,
      "rawEvidenceJson": null,
      "resolutionScope": null,
      "resolvedValue": null,
      "ruleKey": "quantum.arq-q-0321-python",
      "ruleName": "random: non-cryptographic RNG",
      "scanMode": "HEAD_SNAPSHOT",
      "scanPlanName": "quantum-head",
      "semanticKey": null,
      "severity": "HIGH"
    },
    {
      "branchName": "main",
      "detectionSource": "HYBRID",
      "evidenceExcerpt": "generator = random.Random()",
      "exposureScope": "HEAD_ONLY",
      "findingId": "d1fbec61-b3a9-460e-aa5c-101d8bd79725",
      "findingKind": "VULNERABILITY",
      "module": "quantum",
      "presentInHistory": false,
      "presentOnHead": true,
      "primaryFilePath": "app/security/token_factory.py",
      "queryFamily": "python.call-name-match",
      "rawEvidenceJson": "{\"queryRef\":\"python.call-name-match\",\"callName\":\"random.Random\",\"resolutionScope\":\"SAME_FUNCTION\",\"resolvedValue\":\"random.Random\",\"fullName\":\"random.Random\"}",
      "resolutionScope": "SAME_FUNCTION",
      "resolvedValue": "random.Random",
      "ruleKey": "quantum.arq-q-0321-python",
      "ruleName": "random: non-cryptographic RNG",
      "scanMode": "HEAD_SNAPSHOT",
      "scanPlanName": "quantum-head",
      "semanticKey": "python:rng:random.Random:random.Random",
      "severity": "HIGH"
    },
    {
      "branchName": "main",
      "detectionSource": "REGEX",
      "evidenceExcerpt": "import random",
      "exposureScope": "HEAD_ONLY",
      "findingId": "74e43392-fbba-4bfc-ad53-24fbbd5de934",
      "findingKind": "VULNERABILITY",
      "module": "quantum",
      "presentInHistory": false,
      "presentOnHead": true,
      "primaryFilePath": "app/security/token_factory.py",
      "queryFamily": null,
      "rawEvidenceJson": null,
      "resolutionScope": null,
      "resolvedValue": null,
      "ruleKey": "quantum.arq-q-0340-python",
      "ruleName": "random: non-crypto RNG",
      "scanMode": "HEAD_SNAPSHOT",
      "scanPlanName": "quantum-head",
      "semanticKey": null,
      "severity": "HIGH"
    },
    {
      "branchName": "main",
      "detectionSource": "HYBRID",
      "evidenceExcerpt": "generator = random.Random()",
      "exposureScope": "HEAD_ONLY",
      "findingId": "fd0fb86d-7fbf-4d37-8bfa-a696c0ce0939",
      "findingKind": "VULNERABILITY",
      "module": "quantum",
      "presentInHistory": false,
      "presentOnHead": true,
      "primaryFilePath": "app/security/token_factory.py",
      "queryFamily": "python.call-name-match",
      "rawEvidenceJson": "{\"queryRef\":\"python.call-name-match\",\"callName\":\"random.Random\",\"resolutionScope\":\"SAME_FUNCTION\",\"resolvedValue\":\"random.Random\",\"fullName\":\"random.Random\"}",
      "resolutionScope": "SAME_FUNCTION",
      "resolvedValue": "random.Random",
      "ruleKey": "quantum.arq-q-0340-python",
      "ruleName": "random: non-crypto RNG",
      "scanMode": "HEAD_SNAPSHOT",
      "scanPlanName": "quantum-head",
      "semanticKey": "python:rng:random.Random:random.Random",
      "severity": "HIGH"
    },
    {
      "branchName": "main",
      "detectionSource": "HYBRID",
      "evidenceExcerpt": "generator = random.Random()",
      "exposureScope": "HEAD_ONLY",
      "findingId": "0b46d23b-15ab-4212-a6da-4be95838be5c",
      "findingKind": "VULNERABILITY",
      "module": "quantum",
      "presentInHistory": false,
      "presentOnHead": true,
      "primaryFilePath": "app/security/token_factory.py",
      "queryFamily": "python.call-name-match",
      "rawEvidenceJson": "{\"queryRef\":\"python.call-name-match\",\"callName\":\"random.Random\",\"resolutionScope\":\"SAME_FUNCTION\",\"resolvedValue\":\"random.Random\",\"fullName\":\"random.Random\"}",
      "resolutionScope": "SAME_FUNCTION",
      "resolvedValue": "random.Random",
      "ruleKey": "quantum.arq-q-0359-python",
      "ruleName": "random: non-crypto RNG (critical in PQC era)",
      "scanMode": "HEAD_SNAPSHOT",
      "scanPlanName": "quantum-head",
      "semanticKey": "python:rng:random.Random:random.Random",
      "severity": "HIGH"
    },
    {
      "branchName": "main",
      "detectionSource": "REGEX",
      "evidenceExcerpt": "import random",
      "exposureScope": "HEAD_ONLY",
      "findingId": "5b1d2e6f-b8c5-4a67-b65f-65e242c79cce",
      "findingKind": "VULNERABILITY",
      "module": "quantum",
      "presentInHistory": false,
      "presentOnHead": true,
      "primaryFilePath": "app/security/token_factory.py",
      "queryFamily": null,
      "rawEvidenceJson": null,
      "resolutionScope": null,
      "resolvedValue": null,
      "ruleKey": "quantum.arq-q-0359-python",
      "ruleName": "random: non-crypto RNG (critical in PQC era)",
      "scanMode": "HEAD_SNAPSHOT",
      "scanPlanName": "quantum-head",
      "semanticKey": null,
      "severity": "HIGH"
    }
  ],
  "scenarioId": "Q-V4-PY-001",
  "unexpectedFindings": [
    {
      "branchName": "main",
      "detectionSource": "HYBRID",
      "evidenceExcerpt": "return hashlib.md5(payload).hexdigest()",
      "exposureScope": "HEAD_ONLY",
      "findingId": "6ca049fe-d1b8-4e4d-90c0-366295bdb161",
      "findingKind": "VULNERABILITY",
      "module": "quantum",
      "presentInHistory": false,
      "presentOnHead": true,
      "primaryFilePath": "app/security/legacy_signature.py",
      "queryFamily": "python.hashlib",
      "rawEvidenceJson": "{\"queryRef\":\"python.hashlib.weak-digest\",\"callName\":\"hashlib.md5\",\"resolutionScope\":\"SAME_FUNCTION\",\"resolvedValue\":\"MD5\",\"importStyle\":\"MODULE\"}",
      "resolutionScope": "SAME_FUNCTION",
      "resolvedValue": "MD5",
      "ruleKey": "quantum.arq-q-0248-python",
      "ruleName": "hashlib: MD5 digest usage",
      "scanMode": "HEAD_SNAPSHOT",
      "scanPlanName": "quantum-head",
      "semanticKey": "python:hashlib:hashlib.md5:MD5",
      "severity": "HIGH"
    },
    {
      "branchName": "main",
      "detectionSource": "REGEX",
      "evidenceExcerpt": "return hashlib.md5(payload).hexdigest()",
      "exposureScope": "HEAD_ONLY",
      "findingId": "d7975d8a-d305-4841-a92b-bac2b926087b",
      "findingKind": "VULNERABILITY",
      "module": "quantum",
      "presentInHistory": false,
      "presentOnHead": true,
      "primaryFilePath": "app/security/legacy_signature.py",
      "queryFamily": null,
      "rawEvidenceJson": null,
      "resolutionScope": null,
      "resolvedValue": null,
      "ruleKey": "quantum.arq-q-0258-python",
      "ruleName": "hmac: HMAC-MD5 usage",
      "scanMode": "HEAD_SNAPSHOT",
      "scanPlanName": "quantum-head",
      "semanticKey": null,
      "severity": "HIGH"
    },
    {
      "branchName": "main",
      "detectionSource": "HYBRID",
      "evidenceExcerpt": "return hashlib.md5(payload).hexdigest()",
      "exposureScope": "HEAD_ONLY",
      "findingId": "e91af9ce-a19e-4a5d-a74c-468f4d300cb0",
      "findingKind": "VULNERABILITY",
      "module": "quantum",
      "presentInHistory": false,
      "presentOnHead": true,
      "primaryFilePath": "app/security/legacy_signature.py",
      "queryFamily": "python.hashlib",
      "rawEvidenceJson": "{\"queryRef\":\"python.hashlib.weak-digest\",\"callName\":\"hashlib.md5\",\"resolutionScope\":\"SAME_FUNCTION\",\"resolvedValue\":\"MD5\",\"importStyle\":\"MODULE\"}",
      "resolutionScope": "SAME_FUNCTION",
      "resolvedValue": "MD5",
      "ruleKey": "quantum.arq-q-0271-python",
      "ruleName": "hashlib: MD5 usage",
      "scanMode": "HEAD_SNAPSHOT",
      "scanPlanName": "quantum-head",
      "semanticKey": "python:hashlib:hashlib.md5:MD5",
      "severity": "HIGH"
    },
    {
      "branchName": "main",
      "detectionSource": "REGEX",
      "evidenceExcerpt": "return hashlib.md5(payload).hexdigest()",
      "exposureScope": "HEAD_ONLY",
      "findingId": "403209a6-c4b2-445c-97d1-740995dd01c1",
      "findingKind": "VULNERABILITY",
      "module": "quantum",
      "presentInHistory": false,
      "presentOnHead": true,
      "primaryFilePath": "app/security/legacy_signature.py",
      "queryFamily": null,
      "rawEvidenceJson": null,
      "resolutionScope": null,
      "resolvedValue": null,
      "ruleKey": "quantum.arq-q-0277-python",
      "ruleName": "hmac: HMAC with MD5",
      "scanMode": "HEAD_SNAPSHOT",
      "scanPlanName": "quantum-head",
      "semanticKey": null,
      "severity": "HIGH"
    },
    {
      "branchName": "main",
      "detectionSource": "HYBRID",
      "evidenceExcerpt": "return hashlib.md5(payload).hexdigest()",
      "exposureScope": "HEAD_ONLY",
      "findingId": "c4a95240-fcf4-45a6-900d-b6e09d59d235",
      "findingKind": "VULNERABILITY",
      "module": "quantum",
      "presentInHistory": false,
      "presentOnHead": true,
      "primaryFilePath": "app/security/legacy_signature.py",
      "queryFamily": "python.hashlib",
      "rawEvidenceJson": "{\"queryRef\":\"python.hashlib.weak-digest\",\"callName\":\"hashlib.md5\",\"resolutionScope\":\"SAME_FUNCTION\",\"resolvedValue\":\"MD5\",\"importStyle\":\"MODULE\"}",
      "resolutionScope": "SAME_FUNCTION",
      "resolvedValue": "MD5",
      "ruleKey": "quantum.arq-q-0285-python",
      "ruleName": "hashlib: MD5 usage",
      "scanMode": "HEAD_SNAPSHOT",
      "scanPlanName": "quantum-head",
      "semanticKey": "python:hashlib:hashlib.md5:MD5",
      "severity": "HIGH"
    },
    {
      "branchName": "main",
      "detectionSource": "HYBRID",
      "evidenceExcerpt": "return hashlib.md5(payload).hexdigest()",
      "exposureScope": "HEAD_ONLY",
      "findingId": "9e5cca28-2d45-4d52-b65b-7824cc97da42",
      "findingKind": "VULNERABILITY",
      "module": "quantum",
      "presentInHistory": false,
      "presentOnHead": true,
      "primaryFilePath": "app/security/legacy_signature.py",
      "queryFamily": "python.hashlib",
      "rawEvidenceJson": "{\"queryRef\":\"python.hashlib.weak-digest\",\"callName\":\"hashlib.md5\",\"resolutionScope\":\"SAME_FUNCTION\",\"resolvedValue\":\"MD5\",\"importStyle\":\"MODULE\"}",
      "resolutionScope": "SAME_FUNCTION",
      "resolvedValue": "MD5",
      "ruleKey": "quantum.arq-q-0306-python",
      "ruleName": "hashlib: MD5 / SHA1 usage",
      "scanMode": "HEAD_SNAPSHOT",
      "scanPlanName": "quantum-head",
      "semanticKey": "python:hashlib:hashlib.md5:MD5",
      "severity": "HIGH"
    },
    {
      "branchName": "main",
      "detectionSource": "REGEX",
      "evidenceExcerpt": "return hashlib.md5(payload).hexdigest()",
      "exposureScope": "HEAD_ONLY",
      "findingId": "3dabe171-28f8-4010-82cd-3ba8ae41f713",
      "findingKind": "VULNERABILITY",
      "module": "quantum",
      "presentInHistory": false,
      "presentOnHead": true,
      "primaryFilePath": "app/security/legacy_signature.py",
      "queryFamily": null,
      "rawEvidenceJson": null,
      "resolutionScope": null,
      "resolvedValue": null,
      "ruleKey": "quantum.arq-q-0307-python",
      "ruleName": "hashlib: usedforsecurity=False hint misuse",
      "scanMode": "HEAD_SNAPSHOT",
      "scanPlanName": "quantum-head",
      "semanticKey": null,
      "severity": "HIGH"
    },
    {
      "branchName": "main",
      "detectionSource": "HYBRID",
      "evidenceExcerpt": "return hashlib.md5(payload).hexdigest()",
      "exposureScope": "HEAD_ONLY",
      "findingId": "5ae2f357-ccc7-47cc-8ebc-94e79866ed50",
      "findingKind": "VULNERABILITY",
      "module": "quantum",
      "presentInHistory": false,
      "presentOnHead": true,
      "primaryFilePath": "app/security/legacy_signature.py",
      "queryFamily": "python.hashlib",
      "rawEvidenceJson": "{\"queryRef\":\"python.hashlib.weak-digest\",\"callName\":\"hashlib.md5\",\"resolutionScope\":\"SAME_FUNCTION\",\"resolvedValue\":\"MD5\",\"importStyle\":\"MODULE\"}",
      "resolutionScope": "SAME_FUNCTION",
      "resolvedValue": "MD5",
      "ruleKey": "quantum.arq-q-0330-python",
      "ruleName": "hashlib: MD5 / SHA1 usage (critical in mature Python)",
      "scanMode": "HEAD_SNAPSHOT",
      "scanPlanName": "quantum-head",
      "semanticKey": "python:hashlib:hashlib.md5:MD5",
      "severity": "HIGH"
    },
    {
      "branchName": "main",
      "detectionSource": "HYBRID",
      "evidenceExcerpt": "return hashlib.md5(payload).hexdigest()",
      "exposureScope": "HEAD_ONLY",
      "findingId": "c1ab22e9-bc1e-44e2-a0af-58c433116a7b",
      "findingKind": "VULNERABILITY",
      "module": "quantum",
      "presentInHistory": false,
      "presentOnHead": true,
      "primaryFilePath": "app/security/legacy_signature.py",
      "queryFamily": "python.hashlib",
      "rawEvidenceJson": "{\"queryRef\":\"python.hashlib.weak-digest\",\"callName\":\"hashlib.md5\",\"resolutionScope\":\"SAME_FUNCTION\",\"resolvedValue\":\"MD5\",\"importStyle\":\"MODULE\"}",
      "resolutionScope": "SAME_FUNCTION",
      "resolvedValue": "MD5",
      "ruleKey": "quantum.arq-q-0353-python",
      "ruleName": "hashlib: MD5 / SHA1 (critical in PQC-era Python)",
      "scanMode": "HEAD_SNAPSHOT",
      "scanPlanName": "quantum-head",
      "semanticKey": "python:hashlib:hashlib.md5:MD5",
      "severity": "HIGH"
    },
    {
      "branchName": "main",
      "detectionSource": "REGEX",
      "evidenceExcerpt": "import random",
      "exposureScope": "HEAD_ONLY",
      "findingId": "2535c947-99b6-4ff7-8e3a-a8a1bfa60f61",
      "findingKind": "VULNERABILITY",
      "module": "quantum",
      "presentInHistory": false,
      "presentOnHead": true,
      "primaryFilePath": "app/security/token_factory.py",
      "queryFamily": null,
      "rawEvidenceJson": null,
      "resolutionScope": null,
      "resolvedValue": null,
      "ruleKey": "quantum.arq-q-0260-python",
      "ruleName": "random: non-cryptographic RNG for security purposes",
      "scanMode": "HEAD_SNAPSHOT",
      "scanPlanName": "quantum-head",
      "semanticKey": null,
      "severity": "HIGH"
    },
    {
      "branchName": "main",
      "detectionSource": "HYBRID",
      "evidenceExcerpt": "generator = random.Random()",
      "exposureScope": "HEAD_ONLY",
      "findingId": "baa0b024-88c2-423d-a170-2509ce351427",
      "findingKind": "VULNERABILITY",
      "module": "quantum",
      "presentInHistory": false,
      "presentOnHead": true,
      "primaryFilePath": "app/security/token_factory.py",
      "queryFamily": "python.call-name-match",
      "rawEvidenceJson": "{\"queryRef\":\"python.call-name-match\",\"callName\":\"random.Random\",\"resolutionScope\":\"SAME_FUNCTION\",\"resolvedValue\":\"random.Random\",\"fullName\":\"random.Random\"}",
      "resolutionScope": "SAME_FUNCTION",
      "resolvedValue": "random.Random",
      "ruleKey": "quantum.arq-q-0278-python",
      "ruleName": "random: non-cryptographic RNG",
      "scanMode": "HEAD_SNAPSHOT",
      "scanPlanName": "quantum-head",
      "semanticKey": "python:rng:random.Random:random.Random",
      "severity": "HIGH"
    },
    {
      "branchName": "main",
      "detectionSource": "REGEX",
      "evidenceExcerpt": "import random",
      "exposureScope": "HEAD_ONLY",
      "findingId": "c8bd421c-99ce-4237-8a9f-85784b3dfaf9",
      "findingKind": "VULNERABILITY",
      "module": "quantum",
      "presentInHistory": false,
      "presentOnHead": true,
      "primaryFilePath": "app/security/token_factory.py",
      "queryFamily": null,
      "rawEvidenceJson": null,
      "resolutionScope": null,
      "resolvedValue": null,
      "ruleKey": "quantum.arq-q-0278-python",
      "ruleName": "random: non-cryptographic RNG",
      "scanMode": "HEAD_SNAPSHOT",
      "scanPlanName": "quantum-head",
      "semanticKey": null,
      "severity": "HIGH"
    },
    {
      "branchName": "main",
      "detectionSource": "HYBRID",
      "evidenceExcerpt": "generator = random.Random()",
      "exposureScope": "HEAD_ONLY",
      "findingId": "3a41a1d2-c849-4126-b552-1759b73928b5",
      "findingKind": "VULNERABILITY",
      "module": "quantum",
      "presentInHistory": false,
      "presentOnHead": true,
      "primaryFilePath": "app/security/token_factory.py",
      "queryFamily": "python.call-name-match",
      "rawEvidenceJson": "{\"queryRef\":\"python.call-name-match\",\"callName\":\"random.Random\",\"resolutionScope\":\"SAME_FUNCTION\",\"resolvedValue\":\"random.Random\",\"fullName\":\"random.Random\"}",
      "resolutionScope": "SAME_FUNCTION",
      "resolvedValue": "random.Random",
      "ruleKey": "quantum.arq-q-0297-python",
      "ruleName": "random: non-cryptographic RNG",
      "scanMode": "HEAD_SNAPSHOT",
      "scanPlanName": "quantum-head",
      "semanticKey": "python:rng:random.Random:random.Random",
      "severity": "HIGH"
    },
    {
      "branchName": "main",
      "detectionSource": "REGEX",
      "evidenceExcerpt": "import random",
      "exposureScope": "HEAD_ONLY",
      "findingId": "692d45bb-d895-44da-8ff9-abf94649e5d8",
      "findingKind": "VULNERABILITY",
      "module": "quantum",
      "presentInHistory": false,
      "presentOnHead": true,
      "primaryFilePath": "app/security/token_factory.py",
      "queryFamily": null,
      "rawEvidenceJson": null,
      "resolutionScope": null,
      "resolvedValue": null,
      "ruleKey": "quantum.arq-q-0297-python",
      "ruleName": "random: non-cryptographic RNG",
      "scanMode": "HEAD_SNAPSHOT",
      "scanPlanName": "quantum-head",
      "semanticKey": null,
      "severity": "HIGH"
    },
    {
      "branchName": "main",
      "detectionSource": "REGEX",
      "evidenceExcerpt": "import random",
      "exposureScope": "HEAD_ONLY",
      "findingId": "a0c424be-ed3d-4963-9d74-bcc9fd7fd5ad",
      "findingKind": "VULNERABILITY",
      "module": "quantum",
      "presentInHistory": false,
      "presentOnHead": true,
      "primaryFilePath": "app/security/token_factory.py",
      "queryFamily": null,
      "rawEvidenceJson": null,
      "resolutionScope": null,
      "resolvedValue": null,
      "ruleKey": "quantum.arq-q-0321-python",
      "ruleName": "random: non-cryptographic RNG",
      "scanMode": "HEAD_SNAPSHOT",
      "scanPlanName": "quantum-head",
      "semanticKey": null,
      "severity": "HIGH"
    },
    {
      "branchName": "main",
      "detectionSource": "HYBRID",
      "evidenceExcerpt": "generator = random.Random()",
      "exposureScope": "HEAD_ONLY",
      "findingId": "d1fbec61-b3a9-460e-aa5c-101d8bd79725",
      "findingKind": "VULNERABILITY",
      "module": "quantum",
      "presentInHistory": false,
      "presentOnHead": true,
      "primaryFilePath": "app/security/token_factory.py",
      "queryFamily": "python.call-name-match",
      "rawEvidenceJson": "{\"queryRef\":\"python.call-name-match\",\"callName\":\"random.Random\",\"resolutionScope\":\"SAME_FUNCTION\",\"resolvedValue\":\"random.Random\",\"fullName\":\"random.Random\"}",
      "resolutionScope": "SAME_FUNCTION",
      "resolvedValue": "random.Random",
      "ruleKey": "quantum.arq-q-0321-python",
      "ruleName": "random: non-cryptographic RNG",
      "scanMode": "HEAD_SNAPSHOT",
      "scanPlanName": "quantum-head",
      "semanticKey": "python:rng:random.Random:random.Random",
      "severity": "HIGH"
    },
    {
      "branchName": "main",
      "detectionSource": "REGEX",
      "evidenceExcerpt": "import random",
      "exposureScope": "HEAD_ONLY",
      "findingId": "74e43392-fbba-4bfc-ad53-24fbbd5de934",
      "findingKind": "VULNERABILITY",
      "module": "quantum",
      "presentInHistory": false,
      "presentOnHead": true,
      "primaryFilePath": "app/security/token_factory.py",
      "queryFamily": null,
      "rawEvidenceJson": null,
      "resolutionScope": null,
      "resolvedValue": null,
      "ruleKey": "quantum.arq-q-0340-python",
      "ruleName": "random: non-crypto RNG",
      "scanMode": "HEAD_SNAPSHOT",
      "scanPlanName": "quantum-head",
      "semanticKey": null,
      "severity": "HIGH"
    },
    {
      "branchName": "main",
      "detectionSource": "HYBRID",
      "evidenceExcerpt": "generator = random.Random()",
      "exposureScope": "HEAD_ONLY",
      "findingId": "fd0fb86d-7fbf-4d37-8bfa-a696c0ce0939",
      "findingKind": "VULNERABILITY",
      "module": "quantum",
      "presentInHistory": false,
      "presentOnHead": true,
      "primaryFilePath": "app/security/token_factory.py",
      "queryFamily": "python.call-name-match",
      "rawEvidenceJson": "{\"queryRef\":\"python.call-name-match\",\"callName\":\"random.Random\",\"resolutionScope\":\"SAME_FUNCTION\",\"resolvedValue\":\"random.Random\",\"fullName\":\"random.Random\"}",
      "resolutionScope": "SAME_FUNCTION",
      "resolvedValue": "random.Random",
      "ruleKey": "quantum.arq-q-0340-python",
      "ruleName": "random: non-crypto RNG",
      "scanMode": "HEAD_SNAPSHOT",
      "scanPlanName": "quantum-head",
      "semanticKey": "python:rng:random.Random:random.Random",
      "severity": "HIGH"
    },
    {
      "branchName": "main",
      "detectionSource": "HYBRID",
      "evidenceExcerpt": "generator = random.Random()",
      "exposureScope": "HEAD_ONLY",
      "findingId": "0b46d23b-15ab-4212-a6da-4be95838be5c",
      "findingKind": "VULNERABILITY",
      "module": "quantum",
      "presentInHistory": false,
      "presentOnHead": true,
      "primaryFilePath": "app/security/token_factory.py",
      "queryFamily": "python.call-name-match",
      "rawEvidenceJson": "{\"queryRef\":\"python.call-name-match\",\"callName\":\"random.Random\",\"resolutionScope\":\"SAME_FUNCTION\",\"resolvedValue\":\"random.Random\",\"fullName\":\"random.Random\"}",
      "resolutionScope": "SAME_FUNCTION",
      "resolvedValue": "random.Random",
      "ruleKey": "quantum.arq-q-0359-python",
      "ruleName": "random: non-crypto RNG (critical in PQC era)",
      "scanMode": "HEAD_SNAPSHOT",
      "scanPlanName": "quantum-head",
      "semanticKey": "python:rng:random.Random:random.Random",
      "severity": "HIGH"
    },
    {
      "branchName": "main",
      "detectionSource": "REGEX",
      "evidenceExcerpt": "import random",
      "exposureScope": "HEAD_ONLY",
      "findingId": "5b1d2e6f-b8c5-4a67-b65f-65e242c79cce",
      "findingKind": "VULNERABILITY",
      "module": "quantum",
      "presentInHistory": false,
      "presentOnHead": true,
      "primaryFilePath": "app/security/token_factory.py",
      "queryFamily": null,
      "rawEvidenceJson": null,
      "resolutionScope": null,
      "resolvedValue": null,
      "ruleKey": "quantum.arq-q-0359-python",
      "ruleName": "random: non-crypto RNG (critical in PQC era)",
      "scanMode": "HEAD_SNAPSHOT",
      "scanPlanName": "quantum-head",
      "semanticKey": null,
      "severity": "HIGH"
    }
  ],
  "unexpectedRegexOnlyFindings": [
    {
      "branchName": "main",
      "detectionSource": "REGEX",
      "evidenceExcerpt": "return hashlib.md5(payload).hexdigest()",
      "exposureScope": "HEAD_ONLY",
      "findingId": "d7975d8a-d305-4841-a92b-bac2b926087b",
      "findingKind": "VULNERABILITY",
      "module": "quantum",
      "presentInHistory": false,
      "presentOnHead": true,
      "primaryFilePath": "app/security/legacy_signature.py",
      "queryFamily": null,
      "rawEvidenceJson": null,
      "resolutionScope": null,
      "resolvedValue": null,
      "ruleKey": "quantum.arq-q-0258-python",
      "ruleName": "hmac: HMAC-MD5 usage",
      "scanMode": "HEAD_SNAPSHOT",
      "scanPlanName": "quantum-head",
      "semanticKey": null,
      "severity": "HIGH"
    },
    {
      "branchName": "main",
      "detectionSource": "REGEX",
      "evidenceExcerpt": "return hashlib.md5(payload).hexdigest()",
      "exposureScope": "HEAD_ONLY",
      "findingId": "403209a6-c4b2-445c-97d1-740995dd01c1",
      "findingKind": "VULNERABILITY",
      "module": "quantum",
      "presentInHistory": false,
      "presentOnHead": true,
      "primaryFilePath": "app/security/legacy_signature.py",
      "queryFamily": null,
      "rawEvidenceJson": null,
      "resolutionScope": null,
      "resolvedValue": null,
      "ruleKey": "quantum.arq-q-0277-python",
      "ruleName": "hmac: HMAC with MD5",
      "scanMode": "HEAD_SNAPSHOT",
      "scanPlanName": "quantum-head",
      "semanticKey": null,
      "severity": "HIGH"
    },
    {
      "branchName": "main",
      "detectionSource": "REGEX",
      "evidenceExcerpt": "return hashlib.md5(payload).hexdigest()",
      "exposureScope": "HEAD_ONLY",
      "findingId": "3dabe171-28f8-4010-82cd-3ba8ae41f713",
      "findingKind": "VULNERABILITY",
      "module": "quantum",
      "presentInHistory": false,
      "presentOnHead": true,
      "primaryFilePath": "app/security/legacy_signature.py",
      "queryFamily": null,
      "rawEvidenceJson": null,
      "resolutionScope": null,
      "resolvedValue": null,
      "ruleKey": "quantum.arq-q-0307-python",
      "ruleName": "hashlib: usedforsecurity=False hint misuse",
      "scanMode": "HEAD_SNAPSHOT",
      "scanPlanName": "quantum-head",
      "semanticKey": null,
      "severity": "HIGH"
    },
    {
      "branchName": "main",
      "detectionSource": "REGEX",
      "evidenceExcerpt": "import random",
      "exposureScope": "HEAD_ONLY",
      "findingId": "2535c947-99b6-4ff7-8e3a-a8a1bfa60f61",
      "findingKind": "VULNERABILITY",
      "module": "quantum",
      "presentInHistory": false,
      "presentOnHead": true,
      "primaryFilePath": "app/security/token_factory.py",
      "queryFamily": null,
      "rawEvidenceJson": null,
      "resolutionScope": null,
      "resolvedValue": null,
      "ruleKey": "quantum.arq-q-0260-python",
      "ruleName": "random: non-cryptographic RNG for security purposes",
      "scanMode": "HEAD_SNAPSHOT",
      "scanPlanName": "quantum-head",
      "semanticKey": null,
      "severity": "HIGH"
    },
    {
      "branchName": "main",
      "detectionSource": "REGEX",
      "evidenceExcerpt": "import random",
      "exposureScope": "HEAD_ONLY",
      "findingId": "c8bd421c-99ce-4237-8a9f-85784b3dfaf9",
      "findingKind": "VULNERABILITY",
      "module": "quantum",
      "presentInHistory": false,
      "presentOnHead": true,
      "primaryFilePath": "app/security/token_factory.py",
      "queryFamily": null,
      "rawEvidenceJson": null,
      "resolutionScope": null,
      "resolvedValue": null,
      "ruleKey": "quantum.arq-q-0278-python",
      "ruleName": "random: non-cryptographic RNG",
      "scanMode": "HEAD_SNAPSHOT",
      "scanPlanName": "quantum-head",
      "semanticKey": null,
      "severity": "HIGH"
    },
    {
      "branchName": "main",
      "detectionSource": "REGEX",
      "evidenceExcerpt": "import random",
      "exposureScope": "HEAD_ONLY",
      "findingId": "692d45bb-d895-44da-8ff9-abf94649e5d8",
      "findingKind": "VULNERABILITY",
      "module": "quantum",
      "presentInHistory": false,
      "presentOnHead": true,
      "primaryFilePath": "app/security/token_factory.py",
      "queryFamily": null,
      "rawEvidenceJson": null,
      "resolutionScope": null,
      "resolvedValue": null,
      "ruleKey": "quantum.arq-q-0297-python",
      "ruleName": "random: non-cryptographic RNG",
      "scanMode": "HEAD_SNAPSHOT",
      "scanPlanName": "quantum-head",
      "semanticKey": null,
      "severity": "HIGH"
    },
    {
      "branchName": "main",
      "detectionSource": "REGEX",
      "evidenceExcerpt": "import random",
      "exposureScope": "HEAD_ONLY",
      "findingId": "a0c424be-ed3d-4963-9d74-bcc9fd7fd5ad",
      "findingKind": "VULNERABILITY",
      "module": "quantum",
      "presentInHistory": false,
      "presentOnHead": true,
      "primaryFilePath": "app/security/token_factory.py",
      "queryFamily": null,
      "rawEvidenceJson": null,
      "resolutionScope": null,
      "resolvedValue": null,
      "ruleKey": "quantum.arq-q-0321-python",
      "ruleName": "random: non-cryptographic RNG",
      "scanMode": "HEAD_SNAPSHOT",
      "scanPlanName": "quantum-head",
      "semanticKey": null,
      "severity": "HIGH"
    },
    {
      "branchName": "main",
      "detectionSource": "REGEX",
      "evidenceExcerpt": "import random",
      "exposureScope": "HEAD_ONLY",
      "findingId": "74e43392-fbba-4bfc-ad53-24fbbd5de934",
      "findingKind": "VULNERABILITY",
      "module": "quantum",
      "presentInHistory": false,
      "presentOnHead": true,
      "primaryFilePath": "app/security/token_factory.py",
      "queryFamily": null,
      "rawEvidenceJson": null,
      "resolutionScope": null,
      "resolvedValue": null,
      "ruleKey": "quantum.arq-q-0340-python",
      "ruleName": "random: non-crypto RNG",
      "scanMode": "HEAD_SNAPSHOT",
      "scanPlanName": "quantum-head",
      "semanticKey": null,
      "severity": "HIGH"
    },
    {
      "branchName": "main",
      "detectionSource": "REGEX",
      "evidenceExcerpt": "import random",
      "exposureScope": "HEAD_ONLY",
      "findingId": "5b1d2e6f-b8c5-4a67-b65f-65e242c79cce",
      "findingKind": "VULNERABILITY",
      "module": "quantum",
      "presentInHistory": false,
      "presentOnHead": true,
      "primaryFilePath": "app/security/token_factory.py",
      "queryFamily": null,
      "rawEvidenceJson": null,
      "resolutionScope": null,
      "resolvedValue": null,
      "ruleKey": "quantum.arq-q-0359-python",
      "ruleName": "random: non-crypto RNG (critical in PQC era)",
      "scanMode": "HEAD_SNAPSHOT",
      "scanPlanName": "quantum-head",
      "semanticKey": null,
      "severity": "HIGH"
    }
  ],
  "verdict": "PASS_WITH_NOISE",
  "verdictClass": "PASS_WITH_NOISE"
}