{
  "exportedAt": "2026-03-31T23:23:30.825462600Z",
  "exportedCount": 1,
  "format": "json",
  "items": [
    {
      "applicationId": "bedfb47e-5367-4227-8264-0bcc446870c7",
      "applicationKey": "arq-lab-g-v2-hist-009",
      "applicationName": "canonical-wrap-lineage",
      "branchName": "main",
      "commitSha": "30e614164afc46d89f2251d6bd60dbddaa16e4b0",
      "detectionState": "ACTIVE",
      "exposureScope": "HISTORY_ONLY",
      "findingId": "30934db1-4404-4733-84ab-28f1ddf65d66",
      "findingKind": "SECRET",
      "firstSeenAt": "2026-03-31T23:23:27.493009Z",
      "lastSeenAt": "2026-03-31T23:23:27.493009Z",
      "module": "guardian",
      "occurrenceCount": 2,
      "presentInHistory": true,
      "presentOnHead": false,
      "primaryFilePath": "ops/runtime/partner_token.env",
      "primaryLineEnd": 1,
      "primaryLineStart": 1,
      "projectId": "e96d98ba-b3bb-41a1-9c99-b647b0008d4a",
      "projectKey": "arq-lab",
      "projectName": "ARQ Lab Validation",
      "resolvedAt": null,
      "ruleKey": "guardian.generic-api-key",
      "ruleName": "Generic API Key",
      "scanMode": "REF_HISTORY",
      "severity": "MEDIUM",
      "status": "IN_PROGRESS",
      "workflowStatus": "IN_PROGRESS"
    }
  ],
  "limit": 5000,
  "sortBy": "lastSeenAt",
  "sortDirection": "DESC",
  "truncated": false
}