{
  "exportedAt": "2026-04-01T08:24:54.019549800Z",
  "exportedCount": 4,
  "format": "json",
  "items": [
    {
      "applicationId": "713a6058-3982-4246-9886-c929e94a9de4",
      "applicationKey": "arq-lab-g-v1-java-001",
      "applicationName": "payments-service-java",
      "branchName": "main",
      "commitSha": "6a44883704270ae56134b3dffb91d6bb37d31c6f",
      "detectionState": "ACTIVE",
      "exposureScope": "HEAD_ONLY",
      "findingId": "62c9f863-1138-41f4-9d04-c19b44a804d4",
      "findingKind": "SECRET",
      "firstSeenAt": "2026-04-01T08:24:51.748591Z",
      "lastSeenAt": "2026-04-01T08:24:51.748591Z",
      "module": "guardian",
      "occurrenceCount": 1,
      "presentInHistory": false,
      "presentOnHead": true,
      "primaryFilePath": "src/main/java/com/arq/paymentsservicejava/bootstrap/PartnerCredentialBootstrap.java",
      "primaryLineEnd": 2,
      "primaryLineStart": 2,
      "projectId": "b4c13185-a3ed-47a0-b18b-2499403e1969",
      "projectKey": "arq-lab",
      "projectName": "ARQ Lab Validation",
      "resolvedAt": null,
      "ruleKey": "guardian.generic-api-key",
      "ruleName": "Generic API Key",
      "scanMode": "HEAD_SNAPSHOT",
      "severity": "MEDIUM",
      "status": "IN_PROGRESS",
      "workflowStatus": "IN_PROGRESS"
    },
    {
      "applicationId": "713a6058-3982-4246-9886-c929e94a9de4",
      "applicationKey": "arq-lab-g-v1-java-001",
      "applicationName": "payments-service-java",
      "branchName": "main",
      "commitSha": "6a44883704270ae56134b3dffb91d6bb37d31c6f",
      "detectionState": "ACTIVE",
      "exposureScope": "HEAD_ONLY",
      "findingId": "e3171d53-7206-4ec7-a087-9df6fec5c9dc",
      "findingKind": "SECRET",
      "firstSeenAt": "2026-04-01T08:24:51.748591Z",
      "lastSeenAt": "2026-04-01T08:24:51.748591Z",
      "module": "guardian",
      "occurrenceCount": 1,
      "presentInHistory": false,
      "presentOnHead": true,
      "primaryFilePath": "src/main/resources/application-prod.yml",
      "primaryLineEnd": 2,
      "primaryLineStart": 2,
      "projectId": "b4c13185-a3ed-47a0-b18b-2499403e1969",
      "projectKey": "arq-lab",
      "projectName": "ARQ Lab Validation",
      "resolvedAt": null,
      "ruleKey": "guardian.generic-api-key",
      "ruleName": "Generic API Key",
      "scanMode": "HEAD_SNAPSHOT",
      "severity": "MEDIUM",
      "status": "IN_PROGRESS",
      "workflowStatus": "IN_PROGRESS"
    },
    {
      "applicationId": "713a6058-3982-4246-9886-c929e94a9de4",
      "applicationKey": "arq-lab-g-v1-java-001",
      "applicationName": "payments-service-java",
      "branchName": "main",
      "commitSha": "6a44883704270ae56134b3dffb91d6bb37d31c6f",
      "detectionState": "ACTIVE",
      "exposureScope": "HEAD_ONLY",
      "findingId": "645cbb47-c7d8-47b5-be79-ecdab98d10c2",
      "findingKind": "SECRET",
      "firstSeenAt": "2026-04-01T08:24:51.748591Z",
      "lastSeenAt": "2026-04-01T08:24:51.748591Z",
      "module": "guardian",
      "occurrenceCount": 1,
      "presentInHistory": false,
      "presentOnHead": true,
      "primaryFilePath": "src/main/resources/db/seed/live-connector.properties",
      "primaryLineEnd": 1,
      "primaryLineStart": 1,
      "projectId": "b4c13185-a3ed-47a0-b18b-2499403e1969",
      "projectKey": "arq-lab",
      "projectName": "ARQ Lab Validation",
      "resolvedAt": null,
      "ruleKey": "guardian.generic-api-key",
      "ruleName": "Generic API Key",
      "scanMode": "HEAD_SNAPSHOT",
      "severity": "MEDIUM",
      "status": "IN_PROGRESS",
      "workflowStatus": "IN_PROGRESS"
    },
    {
      "applicationId": "713a6058-3982-4246-9886-c929e94a9de4",
      "applicationKey": "arq-lab-g-v1-java-001",
      "applicationName": "payments-service-java",
      "branchName": "main",
      "commitSha": "6a44883704270ae56134b3dffb91d6bb37d31c6f",
      "detectionState": "ACTIVE",
      "exposureScope": "HEAD_ONLY",
      "findingId": "0a6c8f41-afd1-426e-88c0-9de4b177e3ae",
      "findingKind": "SECRET",
      "firstSeenAt": "2026-04-01T08:24:51.748591Z",
      "lastSeenAt": "2026-04-01T08:24:51.748591Z",
      "module": "guardian",
      "occurrenceCount": 1,
      "presentInHistory": false,
      "presentOnHead": true,
      "primaryFilePath": "src/main/resources/keys/partner_rsa.pem",
      "primaryLineEnd": 10,
      "primaryLineStart": 1,
      "projectId": "b4c13185-a3ed-47a0-b18b-2499403e1969",
      "projectKey": "arq-lab",
      "projectName": "ARQ Lab Validation",
      "resolvedAt": null,
      "ruleKey": "guardian.private-key",
      "ruleName": "Private Key",
      "scanMode": "HEAD_SNAPSHOT",
      "severity": "CRITICAL",
      "status": "IN_PROGRESS",
      "workflowStatus": "IN_PROGRESS"
    }
  ],
  "limit": 5000,
  "sortBy": "lastSeenAt",
  "sortDirection": "DESC",
  "truncated": false
}