{
  "plan": {
    "branchScope": "SINGLE_BRANCH",
    "modules": [
      "guardian"
    ],
    "name": "guardian-head-main",
    "refName": "main",
    "scanMode": "HEAD_SNAPSHOT"
  },
  "queued": {
    "applicationId": "3d30d947-6098-48cc-ae82-982d96de5e61",
    "applicationKey": "arq-lab-g-v2-hist-015",
    "applicationName": "branch-private-key-divergence",
    "branchScope": "SINGLE_BRANCH",
    "commitSha": null,
    "connectorId": null,
    "connectorName": null,
    "createdAt": "2026-04-02T00:01:48.925907Z",
    "currentFile": null,
    "currentPhase": "QUEUED",
    "currentRepository": "https://github.com/ARQ-Sec/branch-private-key-divergence.git",
    "failureCode": null,
    "failureMessage": null,
    "filesScanned": 0,
    "filesTotal": 0,
    "finishedAt": null,
    "id": "971b2e59-7e92-440e-82f3-1e31c3de8c59",
    "modules": [
      {
        "findingCount": 0,
        "module": "guardian",
        "occurrenceCount": 0,
        "suppressedCount": 0
      }
    ],
    "parentScanRunId": null,
    "progressPercent": 0,
    "requestedRefName": "main",
    "scanMode": "HEAD_SNAPSHOT",
    "scanType": "APPLICATION",
    "scannedRefName": null,
    "startedAt": null,
    "status": "QUEUED",
    "summary": {},
    "workerNode": null
  }
}