{
  "exportedAt": "2026-04-01T18:12:38.751898800Z",
  "exportedCount": 1,
  "format": "json",
  "items": [
    {
      "applicationId": "06bf0665-8b6c-4bcb-98b9-a7fa8b48ad42",
      "applicationKey": "arq-lab-g-v2-hist-017",
      "applicationName": "move-duplicate-cherrypick-lineage",
      "branchName": "main",
      "commitSha": "130937e0e1ae8f1fb7c03dd8b39c1a1c53fd31c5",
      "detectionState": "ACTIVE",
      "exposureScope": "HISTORY_ONLY",
      "findingId": "b44e4fd3-ecab-4dd5-9960-37d5dea17823",
      "findingKind": "SECRET",
      "firstSeenAt": "2026-04-01T18:12:19.265364Z",
      "lastSeenAt": "2026-04-01T18:12:19.265364Z",
      "module": "guardian",
      "occurrenceCount": 2,
      "presentInHistory": true,
      "presentOnHead": false,
      "primaryFilePath": "src/main/java/com/arq/moveduplicatecherrypicklineage/history/archive/PartnerTokenArchive.java",
      "primaryLineEnd": 2,
      "primaryLineStart": 2,
      "projectId": "e47d6679-e8dc-4ad1-878c-10a86b629b13",
      "projectKey": "arq-lab",
      "projectName": "ARQ Lab Validation",
      "resolvedAt": null,
      "ruleKey": "guardian.generic-api-key",
      "ruleName": "Generic API Key",
      "scanMode": "REF_HISTORY",
      "severity": "MEDIUM",
      "status": "IN_PROGRESS",
      "workflowStatus": "IN_PROGRESS"
    }
  ],
  "limit": 5000,
  "sortBy": "lastSeenAt",
  "sortDirection": "DESC",
  "truncated": false
}