{
  "plan": {
    "branchScope": "SINGLE_BRANCH",
    "modules": [
      "quantum"
    ],
    "name": "quantum-head",
    "refName": "main",
    "scanMode": "HEAD_SNAPSHOT"
  },
  "queued": {
    "applicationId": "8ef702da-2235-4dd5-88a0-c8e6660d32bb",
    "applicationKey": "arq-lab-q-v5-java-003",
    "applicationName": "gateway-config-java",
    "branchScope": "SINGLE_BRANCH",
    "commitSha": null,
    "connectorId": null,
    "connectorName": null,
    "createdAt": "2026-04-02T01:41:09.604035200Z",
    "currentFile": null,
    "currentPhase": "QUEUED",
    "currentRepository": "https://github.com/ARQ-Sec/gateway-config-java.git",
    "failureCode": null,
    "failureMessage": null,
    "filesScanned": 0,
    "filesTotal": 0,
    "finishedAt": null,
    "id": "6d8f7de4-8d04-409c-98ed-c8bc06369c8f",
    "modules": [
      {
        "findingCount": 0,
        "module": "quantum",
        "occurrenceCount": 0,
        "suppressedCount": 0
      }
    ],
    "parentScanRunId": null,
    "progressPercent": 0,
    "requestedRefName": "main",
    "scanMode": "HEAD_SNAPSHOT",
    "scanType": "APPLICATION",
    "scannedRefName": null,
    "startedAt": null,
    "status": "QUEUED",
    "summary": {},
    "workerNode": null
  }
}